pyolap/__init__.py
pyolap/pyolap.py
euclidolap-0.1.1.dist-info/METADATA
euclidolap-0.1.1.dist-info/WHEEL
euclidolap-0.1.1.dist-info/top_level.txt
euclidolap-0.1.1.dist-info/RECORD
